ai_lab_testing-0.2.0.dist-info/licenses/AUTHORS
ai_lab_testing-0.2.0.dist-info/licenses/LICENSE
lab_testing/__init__.py
lab_testing/config.py
lab_testing/exceptions.py
lab_testing/server.py
lab_testing/test_server.py
lab_testing/version.py
lab_testing/resources/__init__.py
lab_testing/resources/device_inventory.py
lab_testing/resources/health.py
lab_testing/resources/help.py
lab_testing/resources/network_status.py
lab_testing/server/__init__.py
lab_testing/server/tool_definitions.py
lab_testing/server/tool_handlers.py
lab_testing/tools/__init__.py
lab_testing/tools/batch_operations.py
lab_testing/tools/batch_operations_async.py
lab_testing/tools/device_manager.py
lab_testing/tools/device_verification.py
lab_testing/tools/network_mapper.py
lab_testing/tools/ota_manager.py
lab_testing/tools/power_analysis.py
lab_testing/tools/power_monitor.py
lab_testing/tools/remote_access.py
lab_testing/tools/tasmota_control.py
lab_testing/tools/vpn_manager.py
lab_testing/tools/vpn_setup.py
lab_testing/utils/__init__.py
lab_testing/utils/change_tracker.py
lab_testing/utils/credentials.py
lab_testing/utils/error_helper.py
lab_testing/utils/logger.py
lab_testing/utils/process_manager.py
lab_testing/utils/ssh_pool.py
ai_lab_testing-0.2.0.dist-info/METADATA
ai_lab_testing-0.2.0.dist-info/WHEEL
ai_lab_testing-0.2.0.dist-info/top_level.txt
ai_lab_testing-0.2.0.dist-info/RECORD
