Metadata-Version: 2.4
Name: ai-lab-testing
Version: 0.2.0
Summary: MCP server for remote embedded hardware testing
Author: Alex J Lennon
Author-email: Alex J Lennon <ajlennon@dynamicdevices.co.uk>
Maintainer: Alex J Lennon
Maintainer-email: Alex J Lennon <ajlennon@dynamicdevices.co.uk>
License: GPL-3.0-or-later
Project-URL: Homepage, https://github.com/DynamicDevices/ai-lab-testing
Project-URL: Documentation, https://github.com/DynamicDevices/ai-lab-testing/blob/main/README.md
Project-URL: Repository, https://github.com/DynamicDevices/ai-lab-testing
Project-URL: Issues, https://github.com/DynamicDevices/ai-lab-testing/issues
Project-URL: Changelog, https://github.com/DynamicDevices/ai-lab-testing/blob/main/CHANGELOG.md
Keywords: mcp,model-context-protocol,embedded,hardware,testing,remote,iot,lab,automation
Classifier: Development Status :: 3 - Alpha
Classifier: Intended Audience :: Developers
Classifier: Topic :: Software Development :: Libraries :: Python Modules
Classifier: Topic :: System :: Hardware
Classifier: Topic :: System :: Networking
Classifier: License :: OSI Approved :: GNU General Public License v3 or later (GPLv3+)
Classifier: Programming Language :: Python :: 3
Classifier: Programming Language :: Python :: 3.10
Classifier: Programming Language :: Python :: 3.11
Classifier: Programming Language :: Python :: 3.12
Classifier: Operating System :: OS Independent
Requires-Python: >=3.8
License-File: LICENSE
License-File: AUTHORS
Requires-Dist: mcp>=1.0.0
Requires-Dist: pydantic>=2.0.0
Requires-Dist: requests>=2.28.0
Provides-Extra: dev
Requires-Dist: black>=23.0.0; extra == "dev"
Requires-Dist: ruff>=0.1.0; extra == "dev"
Requires-Dist: mypy>=1.0.0; extra == "dev"
Requires-Dist: pytest>=7.0.0; extra == "dev"
Dynamic: author
Dynamic: license-file
Dynamic: maintainer
Dynamic: requires-python
